scratchrequest/__init__.py
scratchrequest/_cloud.py
scratchrequest/_exceptions.py
scratchrequest/_project.py
scratchrequest/_session.py
scratchrequest/_settings.py
scratchrequest/_twcloud.py
scratchrequest-0.6.1.dist-info/LICENSE
scratchrequest-0.6.1.dist-info/METADATA
scratchrequest-0.6.1.dist-info/WHEEL
scratchrequest-0.6.1.dist-info/top_level.txt
scratchrequest-0.6.1.dist-info/RECORD
